setup.py
files_SAINT/model.py
files_other/hello.py
files_other/parse_args.py
tabpfn/__init__.py
tabpfn/decoders.py
tabpfn/encoders.py
tabpfn/initializers.py
tabpfn/layer.py
tabpfn/losses.py
tabpfn/model_configs.py
tabpfn/notebook_utils.py
tabpfn/positional_encodings.py
tabpfn/train.py
tabpfn/transformer.py
tabpfn/utils.py
tabpfn/datasets/__init__.py
tabpfn/datasets/utils.py
tabpfn/priors/__init__.py
tabpfn/priors/differentiable_prior.py
tabpfn/priors/fast_gp.py
tabpfn/priors/flexible_categorical.py
tabpfn/priors/mlp.py
tabpfn/priors/prior.py
tabpfn/priors/prior_bag.py
tabpfn/priors/utils.py
tabpfn/scripts/__init__.py
tabpfn/scripts/baseline_prediction_interface.py
tabpfn/scripts/decision_boundary.py
tabpfn/scripts/differentiable_pfn_evaluation.py
tabpfn/scripts/model_builder.py
tabpfn/scripts/model_configs.py
tabpfn/scripts/tabular_baselines.py
tabpfn/scripts/tabular_baselines_deep.py
tabpfn/scripts/tabular_evaluation.py
tabpfn/scripts/tabular_metrics.py
tabpfn/scripts/transformer_prediction_interface.py
tabpfn/tests/__init__.py
tabpfn/tests/test_deterministic_and_model_caching.py
tabpfn/tests/test_follow_sklearn_interface.py
tabpfn/tests/test_load_module_only_inference.py
itabpfn_l1-0.0.4.dist-info/METADATA
itabpfn_l1-0.0.4.dist-info/WHEEL
itabpfn_l1-0.0.4.dist-info/licenses/LICENSE.txt
itabpfn_l1-0.0.4.dist-info/licenses/NOTICE.txt
itabpfn_l1-0.0.4.dist-info/RECORD
